{
    "monday": [
        [
            "00:00"
        ]
    ],
    "tuesday": [
        [
            "00:00"
        ]
    ],
    "wednesday": [
        [
            "00:00"
        ]
    ],
    "thursday": [
        [
            "00:00"
        ]
    ],
    "friday": [
        [
            "19:30"
        ],
        "Overture_-_Super_Mario_Galaxy",
        "Davy_Jones",
        "Test_Drive_From_How_To_Train_Your_Dragon_Music_From_The_Motion_Picture",
        "Loki_Green_Theme",
        "Sky_Peak__Final_Pass_Remaster_Pokemon_Mystery_Dungeon__Explorers_of_Sky",
        "Diana_Boncheva_feat._BanYa_-_Beethoven_Virus_Full_Version",
        "Magnificent_Machines_Steampunk",
        "TV2OP_OPKing_GnuSPECIALZ1156MBS_TBS28"
    ],
    "saturday": [
        [
            "00:00"
        ]
    ],
    "sunday": [
        [
            "00:00"
        ]
    ]
}